miblab/__init__.py
miblab/dlseg.py
miblab/dlsegkidney.py
miblab/report.py
miblab/datafiles/__init__.py
miblab/layout/__init__.py
miblab/layout/tristan-logo.jpg
miblab/static/__init__.py
miblab/static/cover.jpg
miblab/static/epflreport.cls
miblab/static/tristan-logo.jpg
miblab-0.1.0.dist-info/licenses/LICENSE
miblab-0.1.0.dist-info/METADATA
miblab-0.1.0.dist-info/WHEEL
miblab-0.1.0.dist-info/top_level.txt
miblab-0.1.0.dist-info/RECORD
