Metadata-Version: 2.4
Name: miblab
Version: 0.1.0
Summary: Resources of the open laboratory for medical imaging biomarkers
Author-email: Steven Sourbron <s.sourbron@sheffield.ac.uk>
License:                                  Apache License
Project-URL: Homepage, https://miblab.org/
Project-URL: Source Code, https://github.com/openmiblab/miblab
Keywords: python,medical imaging,MRI
Classifier: Development Status :: 3 - Alpha
Classifier: Intended Audience :: Developers
Classifier: Intended Audience :: Science/Research
Classifier: Topic :: Scientific/Engineering
Classifier: Operating System :: OS Independent
Classifier: License :: OSI Approved :: Apache Software License
Classifier: Programming Language :: Python
Classifier: Programming Language :: Python :: 3
Requires-Python: >=3.6
License-File: LICENSE
Requires-Dist: importlib-resources>=1.1.0
Requires-Dist: tqdm
Provides-Extra: report
Requires-Dist: pylatex; extra == "report"
Provides-Extra: dlseg
Requires-Dist: requests; extra == "dlseg"
Requires-Dist: osfclient; extra == "dlseg"
Requires-Dist: vreg; extra == "dlseg"
Requires-Dist: TotalSegmentator; extra == "dlseg"
Requires-Dist: torch; extra == "dlseg"
Requires-Dist: monai==1.3.2; extra == "dlseg"
Requires-Dist: nibabel; extra == "dlseg"
Requires-Dist: scipy; extra == "dlseg"
Dynamic: license-file
